youbit/__init__.py
youbit/__main__.py
youbit/data/README_upload.txt
youbit/decode.py
youbit/detransform.py
youbit/download.py
youbit/ecc/__init__.py
youbit/ecc/creedsolo.c
youbit/ecc/creedsolo.pyx
youbit/ecc/ecc.py
youbit/encode.py
youbit/metadata.py
youbit/settings.py
youbit/tempdir.py
youbit/transform.py
youbit/types.py
youbit/upload.py
youbit/util.py
youbit/video.py
youbit/decode.py
youbit/detransform.py
youbit/download.py
youbit/encode.py
youbit/metadata.py
youbit/settings.py
youbit/tempdir.py
youbit/transform.py
youbit/types.py
youbit/upload.py
youbit/util.py
youbit/video.py
youbit/__init__.py
youbit/__main__.py
youbit/data/README_upload.txt
youbit/ecc/creedsolo.c
youbit/ecc/creedsolo.cp310-win_amd64.pyd
youbit/ecc/creedsolo.pyx
youbit/ecc/ecc.py
youbit/ecc/__init__.py
youbit-2.0.0.dist-info/entry_points.txt
youbit-2.0.0.dist-info/LICENSE
youbit-2.0.0.dist-info/WHEEL
youbit-2.0.0.dist-info/METADATA
youbit-2.0.0.dist-info/RECORD
