Metadata-Version: 2.1
Name: youbit
Version: 2.0.0
Summary: Host any file on YouTube, for free.
Home-page: https://github.com/MeViMo/youbit
License: MIT
Author: Florian Laporte
Author-email: florianl@florianl.dev
Requires-Python: >=3.9,<3.11
Classifier: License :: OSI Approved :: MIT License
Classifier: Programming Language :: Python :: 3
Classifier: Programming Language :: Python :: 3.10
Classifier: Programming Language :: Python :: 3.9
Requires-Dist: av (>=9.2.0,<10.0.0)
Requires-Dist: browser-cookie3 (>=0.15.0,<0.16.0)
Requires-Dist: numba (>=0.55.2,<0.56.0)
Requires-Dist: rich (>=12.4.4,<13.0.0)
Requires-Dist: selenium (>=4.2.0,<5.0.0)
Requires-Dist: typer (>=0.4.1,<0.5.0)
Requires-Dist: webdriver-manager (>=3.7.0,<4.0.0)
Requires-Dist: yt-dlp (>=2022.5.18,<2023.0.0)
Project-URL: Repository, https://github.com/MeViMo/youbit
